gumshoe/__init__.py
gumshoe/main.py
gumshoe/classes/__init__.py
gumshoe/classes/activity.py
gumshoe/classes/gumshoecli.py
gumshoe/classes/habits.py
gumshoe/commands/__init__.py
gumshoe/commands/complete.py
gumshoe/commands/create.py
gumshoe/commands/remove.py
gumshoe/commands/show.py
gumshoe/database/__init__.py
gumshoe/documentation/__init__.py
gumshoe/logs/__init__.py
gumshoe/models/__init__.py
gumshoe/models/models.py
gumshoe_cli-1.1.9.dist-info/LICENSE
gumshoe_cli-1.1.9.dist-info/METADATA
gumshoe_cli-1.1.9.dist-info/WHEEL
gumshoe_cli-1.1.9.dist-info/entry_points.txt
gumshoe_cli-1.1.9.dist-info/top_level.txt
gumshoe_cli-1.1.9.dist-info/RECORD
